<DistDoc action="add" dist="dist_id" distdocver="05.1" an="STIMES0020180327ee3s0049h" doctype="article"><SelectData><FolderName id="302210954" rl="100">BT, TODAY and Straits</FolderName></SelectData><ReplyItem lang="en"><BaseLang value="en" fid="la"/><IPDocId fid="id">STIMES0020180327ee3s0049h</IPDocId><AccessionNo value="STIMES0020180327ee3s0049h" fid="an"/><Num value="354" fid="wc"/><Date value="20180328" fid="pd"/><SrcCode value="stimes" fid="sc"/><SrcName fid="sn">The Straits Times</SrcName><TruncRules><XS value="27"/></TruncRules><Title fid="hl"><SectionName fid="se">Life</SectionName><ColumnName fid="clm"></ColumnName><Headline fid="hd"><Para lang="en">HK actor Wong reunites with Australia-based half-brothers</Para></Headline></Title><Snippet><Para>Famed Hong Kong actor Anthony Wong has been reunited with two older half-brothers he never knew, thanks to a BBC report on his search for his long-lost father.</Para></Snippet><Byline fid="by"></Byline><Credit fid="cr"></Credit><Copyright fid="cy">(c) 2018 Singapore Press Holdings Limited </Copyright><CodeSets><CSet fid="re"><Code value="austr"/><Code value="hkong"/><Code value="apacz"/><Code value="asiaz"/><Code value="ausnz"/><Code value="bric"/><Code value="china"/><Code value="chinaz"/><Code value="devgcoz"/><Code value="dvpcoz"/><Code value="easiaz"/></CSet><CSet fid="ns"><Code value="gcele"/><Code value="glife"/><Code value="gcat"/></CSet></CodeSets></ReplyItem><MetadataPT><DocData><DocType value="article" fid="fmt"/><IPDocId fid="id">STIMES0020180327ee3s0049h</IPDocId><AccessionNo value="STIMES0020180327ee3s0049h" fid="an"/><Num value="354" fid="wc"/><Num value="1539" fid="cc"/><Date value="20180328" fid="pd"/><Date value="20180327" fid="upd"/><Date value="20180327" fid="md"/><Time value="234523" fid="upt"/><Time value="234523" fid="mt"/><BaseLang value="en" fid="la"/><Editor value="" fid="rve"/><RevisionNo value="0" fid="rvn"/></DocData><PubData><Restrictor fid="rst"><Code value="FSPNORMAWS0300"/><Code value="STIMES"/><Code value="fspFileId277629244"/><Code value="FUT"/><Code value="ASIA"/><Code value="CLNTBLK"/><Code value="EN"/><Code value="SEASIAZ"/><Code value="SFSTR"/><Code value="SINGP"/><Code value="TAPN"/><Code value="TBNC"/><Code value="TFCDLIC"/><Code value="TGPW"/><Code value="TIBMNB"/><Code value="TMNB"/><Code value="TMNBAS"/><Code value="TNST"/><Code value="TNWP"/><Code value="TNWPN"/><Code value="TSCH"/><Code value="TTRK"/><Code value="TYAS"/><Code value="TYLA"/><Code value="MPCV1M9M1B1"/><Code value="MPCEnvPROD"/><Code value="MPCDocHash97D5BD2CF0DB617E"/><Code value="FSP2YESCOOC"/><Code value="FSP2YESCOCOMOC"/><Code value="FSPRBC"/><Code value="FSPRBCNS"/><Code value="FSP2YESNS"/><Code value="FSPCATEGORIZER"/><Code value="FSPCATRE"/><Code value="FSP2YESRE"/><Code value="FSPRBCRE"/><Code value="FSP2NOCO"/><Code value="FSP2NOIN"/><Code value="FSP2NOPEOC"/><Code value="FSPRBC262544"/><Code value="FSPRBC624958"/><Code value="FSPRBC695199"/><Code value="FSPRBC816345"/><Code value="FSPRBC847446"/><Code value="FSPRBC853402"/><Code value="MPCCL"/><Code value="MPCJP"/><Code value="MPCKW"/><Code value="MPCKP"/><Code value="MPCESRE"/><Code value="MPCESIN"/><Code value="MPCESNS"/><Code value="FSP2AC"/></Restrictor><IPId value="SPH" fid="ip"/><PublisherN fid="pub">Singapore Press Holdings Limited</PublisherN><AttribCode value="STIMES" fid="atr"/><SrcCode value="STIMES" fid="sc"/><SrcName fid="sn">The Straits Times</SrcName><Logo img="stimesLogo.gif" link="" src="http://logos.factiva.com"/></PubData><CodeSets><CSet fid="re"><Code value="austr"><CodeD index="no" lang="en">Australia</CodeD><CodeI org="categoriser" action="add"><CodeA name="db" value="es-EnglishRE_en_20180319142019"/><CodeA name="es_score" value="84"/></CodeI><CodeI org="validation" action="add"><CodeA name="db" value="pedv---00001004-20180327-161428"/><CodeA name="status" value="active"/></CodeI><CodeI org="hierarchy" action="add"><CodeA name="db" value="pedv---00001004-20180327-161428"/><CodeA name="nodelevel" value="1"/><CodeA name="nodelevel" value="2"/></CodeI></Code><Code value="hkong"><CodeD index="no" lang="en">Hong Kong</CodeD><CodeI org="rbc" action="add"><CodeA name="rule" value="853402"/><CodeA name="db" value="prbc---00018592-20180327-145232"/><CodeA name="rule" value="624958"/></CodeI><CodeI org="validation" action="add"><CodeA name="db" value="pedv---00001004-20180327-161428"/><CodeA name="status" value="active"/></CodeI><CodeI org="hierarchy" action="add"><CodeA name="db" value="pedv---00001004-20180327-161428"/><CodeA name="nodelevel" value="2"/><CodeA name="nodelevel" value="3"/><CodeA name="nodelevel" value="4"/></CodeI></Code><Code value="apacz"><CodeD index="no" lang="en">Asia Pacific</CodeD><CodeI org="expansion" action="add"><CodeA name="db" value="pedv---00001004-20180327-161428"/><CodeA name="root" value="re:austr"/><CodeA name="root" value="re:hkong"/></CodeI><CodeI org="validation" action="add"><CodeA name="db" value="pedv---00001004-20180327-161428"/><CodeA name="status" value="active"/></CodeI><CodeI org="hierarchy" action="add"><CodeA name="db" value="pedv---00001004-20180327-161428"/><CodeA name="nodelevel" value="0"/></CodeI></Code><Code value="asiaz"><CodeD index="no" lang="en">Asia</CodeD><CodeI org="expansion" action="add"><CodeA name="db" value="pedv---00001004-20180327-161428"/><CodeA name="root" value="re:hkong"/></CodeI><CodeI org="validation" action="add"><CodeA name="db" value="pedv---00001004-20180327-161428"/><CodeA name="status" value="active"/></CodeI><CodeI org="hierarchy" action="add"><CodeA name="db" value="pedv---00001004-20180327-161428"/><CodeA name="nodelevel" value="0"/></CodeI></Code><Code value="ausnz"><CodeD index="no" lang="en">Australia/Oceania</CodeD><CodeI org="expansion" action="add"><CodeA name="db" value="pedv---00001004-20180327-161428"/><CodeA name="root" value="re:austr"/></CodeI><CodeI org="validation" action="add"><CodeA name="db" value="pedv---00001004-20180327-161428"/><CodeA name="status" value="active"/></CodeI><CodeI org="hierarchy" action="add"><CodeA name="db" value="pedv---00001004-20180327-161428"/><CodeA name="nodelevel" value="0"/><CodeA name="nodelevel" value="1"/></CodeI></Code><Code value="bric"><CodeD index="no" lang="en">BRICS Countries</CodeD><CodeI org="expansion" action="add"><CodeA name="db" value="pedv---00001004-20180327-161428"/><CodeA name="root" value="re:hkong"/></CodeI><CodeI org="validation" action="add"><CodeA name="db" value="pedv---00001004-20180327-161428"/><CodeA name="status" value="active"/></CodeI><CodeI org="hierarchy" action="add"><CodeA name="db" value="pedv---00001004-20180327-161428"/><CodeA name="nodelevel" value="1"/></CodeI></Code><Code value="china"><CodeD index="no" lang="en">China</CodeD><CodeI org="expansion" action="add"><CodeA name="db" value="pedv---00001004-20180327-161428"/><CodeA name="root" value="re:hkong"/></CodeI><CodeI org="validation" action="add"><CodeA name="db" value="pedv---00001004-20180327-161428"/><CodeA name="status" value="active"/></CodeI><CodeI org="hierarchy" action="add"><CodeA name="db" value="pedv---00001004-20180327-161428"/><CodeA name="nodelevel" value="1"/><CodeA name="nodelevel" value="2"/><CodeA name="nodelevel" value="3"/></CodeI></Code><Code value="chinaz"><CodeD index="no" lang="en">Greater China</CodeD><CodeI org="expansion" action="add"><CodeA name="db" value="pedv---00001004-20180327-161428"/><CodeA name="root" value="re:hkong"/></CodeI><CodeI org="validation" action="add"><CodeA name="db" value="pedv---00001004-20180327-161428"/><CodeA name="status" value="active"/></CodeI><CodeI org="hierarchy" action="add"><CodeA name="db" value="pedv---00001004-20180327-161428"/><CodeA name="nodelevel" value="2"/></CodeI></Code><Code value="devgcoz"><CodeD index="no" lang="en">Emerging Market Countries</CodeD><CodeI org="expansion" action="add"><CodeA name="db" value="pedv---00001004-20180327-161428"/><CodeA name="root" value="re:hkong"/></CodeI><CodeI org="validation" action="add"><CodeA name="db" value="pedv---00001004-20180327-161428"/><CodeA name="status" value="active"/></CodeI><CodeI org="hierarchy" action="add"><CodeA name="db" value="pedv---00001004-20180327-161428"/><CodeA name="nodelevel" value="0"/></CodeI></Code><Code value="dvpcoz"><CodeD index="no" lang="en">Developing Economies</CodeD><CodeI org="expansion" action="add"><CodeA name="db" value="pedv---00001004-20180327-161428"/><CodeA name="root" value="re:hkong"/></CodeI><CodeI org="validation" action="add"><CodeA name="db" value="pedv---00001004-20180327-161428"/><CodeA name="status" value="active"/></CodeI><CodeI org="hierarchy" action="add"><CodeA name="db" value="pedv---00001004-20180327-161428"/><CodeA name="nodelevel" value="0"/></CodeI></Code><Code value="easiaz"><CodeD index="no" lang="en">Eastern Asia</CodeD><CodeI org="expansion" action="add"><CodeA name="db" value="pedv---00001004-20180327-161428"/><CodeA name="root" value="re:hkong"/></CodeI><CodeI org="validation" action="add"><CodeA name="db" value="pedv---00001004-20180327-161428"/><CodeA name="status" value="active"/></CodeI><CodeI org="hierarchy" action="add"><CodeA name="db" value="pedv---00001004-20180327-161428"/><CodeA name="nodelevel" value="1"/></CodeI></Code></CSet><CSet fid="ns"><Code value="gcele"><CodeD index="no" lang="en">Celebrities</CodeD><CodeI org="rbc" action="add"><CodeA name="rule" value="816345"/><CodeA name="db" value="prbc---00018592-20180327-145232"/></CodeI><CodeI org="validation" action="add"><CodeA name="db" value="pedv---00001004-20180327-161428"/><CodeA name="status" value="active"/></CodeI><CodeI org="hierarchy" action="add"><CodeA name="db" value="pedv---00001004-20180327-161428"/><CodeA name="nodelevel" value="2"/></CodeI></Code><Code value="glife"><CodeD index="no" lang="en">Living/Lifestyle</CodeD><CodeI org="rbc" action="add"><CodeA name="rule" value="847446"/><CodeA name="db" value="prbc---00018592-20180327-145232"/></CodeI><CodeI org="expansion" action="add"><CodeA name="db" value="pedv---00001004-20180327-161428"/><CodeA name="root" value="ns:gcele"/></CodeI><CodeI org="validation" action="add"><CodeA name="db" value="pedv---00001004-20180327-161428"/><CodeA name="status" value="active"/></CodeI><CodeI org="hierarchy" action="add"><CodeA name="db" value="pedv---00001004-20180327-161428"/><CodeA name="nodelevel" value="1"/></CodeI></Code><Code value="gcat"><CodeD index="no" lang="en">Political/General News</CodeD><CodeI org="expansion" action="add"><CodeA name="db" value="pedv---00001004-20180327-161428"/><CodeA name="root" value="ns:gcele"/><CodeA name="root" value="ns:glife"/></CodeI><CodeI org="validation" action="add"><CodeA name="db" value="pedv---00001004-20180327-161428"/><CodeA name="status" value="active"/></CodeI><CodeI org="hierarchy" action="add"><CodeA name="db" value="pedv---00001004-20180327-161428"/><CodeA name="nodelevel" value="0"/></CodeI></Code></CSet></CodeSets></MetadataPT><ArchiveDoc xml:space="preserve"><Article markup="pp0" lang="en" index="field"><HandL fid="hlp"><Title fid="hl"><SectionName fid="se" index="field">Life</SectionName><ColumnName fid="clm" index="field"></ColumnName><Headline fid="hd"><Para lang="en">HK actor Wong reunites with Australia-based half-brothers</Para></Headline></Title><LeadPara fid="lp"><Para>Famed Hong Kong actor Anthony Wong has been reunited with two older half-brothers he never knew, thanks to a BBC report on his search for his long-lost father.</Para><Para>BBC shared a video of the family reunion online on Tuesday. In it, Wong, 56, speaks emotionally about meeting his twin 74-year-old siblings, Australia-based John and David Perry.</Para></LeadPara></HandL><TailParas fid="td"><Para>The actor says in a mix of English and subtitled Cantonese: "I thought, 'How on earth did this happen? Amazing, impossible, a miracle.'"</Para><Para>The award-winning star of movies such as Infernal Affairs (2002) spoke in a Feb 28 interview with BBC China about wanting to reconnect with his father, a former British Hong Kong government official. He was only four when his father left the family home.</Para><Para>BBC reports that the actor had only a few photos of his English father, Frederick Perry, to help. He was brought up by his Cantonese mother in Hong Kong.</Para><Para>BBC published the news of his search in end February and viewers set up a Facebook thread to help.</Para><Para>On March 2, Wong revealed on Facebook that someone might have found his long-lost family.</Para><Para>The post said: "Someone found this information of my father: Frederick William Perry born 11 June 1914 arrived in Hong Kong in 1955 with wife Vera Marjorie born 8 September 1919. One daughter, Vera Ann born 2 December 1940 and twin sons, John William and David Frederick born 29 June 1943."</Para><Para>The link led to the Perrys, who had never heard about their father's other son and had no idea that he was a famous figure in Hong Kong cinema.</Para><Para>The brothers flew to Hong Kong to meet the actor and the BBC video shows the men embracing and deciding to call themselves "The Three Musketeers".</Para><Para>The Perrys shared photos of their father with Wong, while Wong introduced his brothers to his movies.</Para><Para>He said to BBC: "I think (my father) knows I've been a good boy since (he left), so he sent two brothers to me."</Para></TailParas><Byline fid="by" index="field"></Byline><Credit fid="cr" index="field"></Credit><Contact fid="ct" index="field"></Contact><Notes fid="rf" index="field"></Notes><Art fid="art" index="field">Anthony Wong </Art><Copyright fid="cy" index="field">(c) 2018 Singapore Press Holdings Limited </Copyright></Article></ArchiveDoc><AdocTOC adoctype="article"><Item size="0" ref="distdoc:archive/ArchiveDoc::Article" type="arttext"></Item><Item size="0" ref="distdoc:archive/InvertText" type="invtext"></Item></AdocTOC></DistDoc>

