<DistDoc action="add" dist="dist_id" distdocver="05.1" an="TDAYSG0020180327ee3r00002" doctype="article"><SelectData><FolderName id="302210954" rl="100">BT, TODAY and Straits</FolderName><FolderName id="302210842" rl="100">FNA Asian Economics</FolderName><FolderName id="302210876" rl="100">FNA Singapore Economics</FolderName></SelectData><ReplyItem lang="en"><BaseLang value="en" fid="la"/><IPDocId fid="id">TDAYSG0020180327ee3r00002</IPDocId><AccessionNo value="TDAYSG0020180327ee3r00002" fid="an"/><Num value="643" fid="wc"/><Date value="20180327" fid="pd"/><SrcCode value="tdaysg" fid="sc"/><SrcName fid="sn">TODAY</SrcName><TruncRules><XS value="30"/></TruncRules><Title fid="hl"><SectionName fid="se">Singapore</SectionName><ColumnName fid="clm"></ColumnName><Headline fid="hd"><Para lang="en">More Singaporeans gambling but hardcore gamblers hold steady </Para></Headline></Title><Snippet><Para>SINGAPORE – More Singapore residents could be gambling and probable hardcore gamblers are betting much more than before, although their numbers have held steady, according to the National Council on Problem Gambling’s (NCPG) latest survey.</Para></Snippet><Byline fid="by">Siau Ming En </Byline><Credit fid="cr"></Credit><Copyright fid="cy">(c) 2018. MediaCorp Press Ltd. </Copyright><CodeSets><CSet fid="re"><Code value="singp"/><Code value="apacz"/><Code value="asiaz"/><Code value="seasiaz"/></CSet><CSet fid="ns"><Code value="gcgamb"/><Code value="nsur"/><Code value="gcat"/><Code value="gcom"/><Code value="gsoc"/><Code value="ncat"/></CSet></CodeSets></ReplyItem><MetadataPT><DocData><DocType value="article" fid="fmt"/><IPDocId fid="id">TDAYSG0020180327ee3r00002</IPDocId><AccessionNo value="TDAYSG0020180327ee3r00002" fid="an"/><Num value="643" fid="wc"/><Num value="3023" fid="cc"/><Date value="20180327" fid="pd"/><Date value="20180327" fid="upd"/><Date value="20180327" fid="md"/><Time value="221519" fid="upt"/><Time value="221519" fid="mt"/><PubEdition fid="ed">APM</PubEdition><PubPage fid="pg">1</PubPage><BaseLang value="en" fid="la"/><Editor value="" fid="rve"/><RevisionNo value="0" fid="rvn"/></DocData><PubData><Restrictor fid="rst"><Code value="FSPNORMAWS0300"/><Code value="TDAYSG"/><Code value="fspFileId277611688"/><Code value="FUT"/><Code value="ASIA"/><Code value="CLNTALL"/><Code value="EN"/><Code value="SEASIAZ"/><Code value="SINGP"/><Code value="TAPN"/><Code value="TNST"/><Code value="TNWP"/><Code value="TNWPR"/><Code value="TSCH"/><Code value="TTRK"/><Code value="TYAS"/><Code value="TYLB"/><Code value="TDAYSG"/><Code value="djsipif"/><Code value="MPCV1M9M1B1"/><Code value="MPCEnvPROD"/><Code value="MPCDocHashB9858AB67A4CA5C4"/><Code value="FSP2YESCOOC"/><Code value="FSP2YESCOCOMOC"/><Code value="FSPCATEGORIZER"/><Code value="FSPCATNS"/><Code value="FSP2YESNS"/><Code value="FSPRBC"/><Code value="FSPRBCNS"/><Code value="FSPCATRE"/><Code value="FSPRBCRE"/><Code value="FSP2YESRE"/><Code value="FSP2NOCO"/><Code value="FSP2NOIN"/><Code value="FSP2NOPEOC"/><Code value="FSPRBC621444"/><Code value="FSPRBC624350"/><Code value="FSPRBC817538"/><Code value="MPCCL"/><Code value="MPCJP"/><Code value="MPCKW"/><Code value="MPCKP"/><Code value="MPCESRE"/><Code value="MPCESIN"/><Code value="MPCESNS"/><Code value="FSP2AC"/></Restrictor><IPId value="MDCRP" fid="ip"/><PublisherN fid="pub">MediaCorp Press Ltd</PublisherN><AttribCode value="TDAYSG" fid="atr"/><SrcCode value="TDAYSG" fid="sc"/><SrcName fid="sn">TODAY</SrcName><Logo img="tdaysgLogo.gif" link="" src="http://logos.factiva.com"/></PubData><CodeSets><CSet fid="re"><Code value="singp"><CodeD index="no" lang="en">Singapore</CodeD><CodeI org="categoriser" action="add"><CodeA name="db" value="es-EnglishRE_en_20180319142019"/><CodeA name="es_score" value="200"/></CodeI><CodeI org="rbc" action="add"><CodeA name="rule" value="621444"/><CodeA name="db" value="prbc---00018592-20180327-145232"/></CodeI><CodeI org="validation" action="add"><CodeA name="db" value="pedv---00001004-20180327-161428"/><CodeA name="status" value="active"/></CodeI><CodeI org="hierarchy" action="add"><CodeA name="db" value="pedv---00001004-20180327-161428"/><CodeA name="nodelevel" value="2"/></CodeI></Code><Code value="apacz"><CodeD index="no" lang="en">Asia Pacific</CodeD><CodeI org="expansion" action="add"><CodeA name="db" value="pedv---00001004-20180327-161428"/><CodeA name="root" value="re:singp"/></CodeI><CodeI org="validation" action="add"><CodeA name="db" value="pedv---00001004-20180327-161428"/><CodeA name="status" value="active"/></CodeI><CodeI org="hierarchy" action="add"><CodeA name="db" value="pedv---00001004-20180327-161428"/><CodeA name="nodelevel" value="0"/></CodeI></Code><Code value="asiaz"><CodeD index="no" lang="en">Asia</CodeD><CodeI org="expansion" action="add"><CodeA name="db" value="pedv---00001004-20180327-161428"/><CodeA name="root" value="re:singp"/></CodeI><CodeI org="validation" action="add"><CodeA name="db" value="pedv---00001004-20180327-161428"/><CodeA name="status" value="active"/></CodeI><CodeI org="hierarchy" action="add"><CodeA name="db" value="pedv---00001004-20180327-161428"/><CodeA name="nodelevel" value="0"/></CodeI></Code><Code value="seasiaz"><CodeD index="no" lang="en">Southeast Asia</CodeD><CodeI org="expansion" action="add"><CodeA name="db" value="pedv---00001004-20180327-161428"/><CodeA name="root" value="re:singp"/></CodeI><CodeI org="validation" action="add"><CodeA name="db" value="pedv---00001004-20180327-161428"/><CodeA name="status" value="active"/></CodeI><CodeI org="hierarchy" action="add"><CodeA name="db" value="pedv---00001004-20180327-161428"/><CodeA name="nodelevel" value="1"/></CodeI></Code></CSet><CSet fid="ns"><Code value="gcgamb"><CodeD index="no" lang="en">Compulsive Gambling</CodeD><CodeI org="categoriser" action="add"><CodeA name="db" value="es-EnglishNS_en_20180322142639"/><CodeA name="es_score" value="360"/></CodeI><CodeI org="validation" action="add"><CodeA name="db" value="pedv---00001004-20180327-161428"/><CodeA name="status" value="active"/></CodeI><CodeI org="hierarchy" action="add"><CodeA name="db" value="pedv---00001004-20180327-161428"/><CodeA name="nodelevel" value="3"/></CodeI></Code><Code value="nsur"><CodeD index="no" lang="en">Surveys/Polls</CodeD><CodeI org="rbc" action="add"><CodeA name="rule" value="624350"/><CodeA name="db" value="prbc---00018592-20180327-145232"/></CodeI><CodeI org="validation" action="add"><CodeA name="db" value="pedv---00001004-20180327-161428"/><CodeA name="status" value="active"/></CodeI></Code><Code value="gcat"><CodeD index="no" lang="en">Political/General News</CodeD><CodeI org="expansion" action="add"><CodeA name="db" value="pedv---00001004-20180327-161428"/><CodeA name="root" value="ns:gcgamb"/></CodeI><CodeI org="validation" action="add"><CodeA name="db" value="pedv---00001004-20180327-161428"/><CodeA name="status" value="active"/></CodeI><CodeI org="hierarchy" action="add"><CodeA name="db" value="pedv---00001004-20180327-161428"/><CodeA name="nodelevel" value="0"/></CodeI></Code><Code value="gcom"><CodeD index="no" lang="en">Society/Community</CodeD><CodeI org="expansion" action="add"><CodeA name="db" value="pedv---00001004-20180327-161428"/><CodeA name="root" value="ns:gcgamb"/></CodeI><CodeI org="validation" action="add"><CodeA name="db" value="pedv---00001004-20180327-161428"/><CodeA name="status" value="active"/></CodeI><CodeI org="hierarchy" action="add"><CodeA name="db" value="pedv---00001004-20180327-161428"/><CodeA name="nodelevel" value="1"/></CodeI></Code><Code value="gsoc"><CodeD index="no" lang="en">Social Issues</CodeD><CodeI org="expansion" action="add"><CodeA name="db" value="pedv---00001004-20180327-161428"/><CodeA name="root" value="ns:gcgamb"/></CodeI><CodeI org="validation" action="add"><CodeA name="db" value="pedv---00001004-20180327-161428"/><CodeA name="status" value="active"/></CodeI><CodeI org="hierarchy" action="add"><CodeA name="db" value="pedv---00001004-20180327-161428"/><CodeA name="nodelevel" value="2"/></CodeI></Code><Code value="ncat"><CodeD index="no" lang="en">Content Types</CodeD><CodeI org="expansion" action="add"><CodeA name="db" value="pedv---00001004-20180327-161428"/><CodeA name="root" value="ns:nsur"/></CodeI><CodeI org="validation" action="add"><CodeA name="db" value="pedv---00001004-20180327-161428"/><CodeA name="status" value="active"/></CodeI></Code></CSet></CodeSets><DescTPC fid="de"><DescField fid="ipd">Community </DescField></DescTPC></MetadataPT><ArchiveDoc xml:space="preserve"><Article markup="pp0" lang="en" index="field"><HandL fid="hlp"><Title fid="hl"><SectionName fid="se" index="field">Singapore</SectionName><ColumnName fid="clm" index="field"></ColumnName><Headline fid="hd"><Para lang="en">More Singaporeans gambling but hardcore gamblers hold steady </Para></Headline></Title><LeadPara fid="lp"><Para>SINGAPORE – More Singapore residents could be gambling and probable hardcore gamblers are betting much more than before, although their numbers have held steady, according to the National Council on Problem Gambling’s (NCPG) latest survey.</Para><Para>Probable hardcore gamblers – or probable pathological gamblers, those with the most severe form of the addiction – made up 0.1 per cent of the 3,000 Singapore residents aged 18 and above polled in the NCPG’s 2017 Gambling Participation survey.</Para></LeadPara></HandL><TailParas fid="td"><Para>The figure is slightly lower than the 0.2 per cent in the previous survey conducted in 2014.</Para><Para>Their median wagers, however, more than triple from S$80 to S$250 a month.</Para><Para>Together with the respondents who were likely problem gamblers – albeit not as serious as the probable pathological gamblers – they made up 0.9 per cent of the respondents, up slightly from 0.7 per cent in 2014.</Para><Para>However, the 2017 survey found that the share of people gambling had gone up. Those who said they had participated in at least one form of gambling in the preceding year increased from 44 per cent in 2014 to 52 per cent in 2017, bucking a decline seen since 2008.</Para><Para>Their median betting amounts also increased from S$20 in 2014, to S$30 last year.</Para><Para>The NCPG could not explain the increase in betting amounts but said the sums hardcore gamblers are putting down is a concern.</Para><Para>“(The probably pathological gamblers) have poor self-control... We should be concerned that (they) are gambling more because compared to the normal gambler, they are more likely to regret spending more money than (they planned to),” said the council.</Para><Para>The survey found a significant increase in proportion of those buying 4D, Toto and partaking in social gambling.</Para><Para>Chinese and males were found to have a higher gambling participation rate.</Para><Para>Addiction management expert Thomas Lee of The Resilienz Clinic said it is difficult to assess if amounts betted by his clients are excessive, but said their gambling becomes a problem when they bet more than they can afford to. This could mean betting their entire month’s salary or asking for advance salary to fund their gambling activities, he said.</Para><Para>The Resilienz Clinic is one of the NCPG’s appointed agencies for problem gamblers.</Para><Para>Some punters may be addicted to “soft” forms of gambling such as buying 4D and Toto, when they adopt distorted beliefs, such as the need to buy 4D when they encounter events out of the ordinary, such as a road accident, he said. They may become entrapped in the belief that they have to continue betting to recover the “investments” made previously, said Dr Lee, a consultant psychiatrist.</Para><Para>Last year, 12.5 per cent of those counselled by Credit Counselling Singapore cited gambling as one of the reasons for their debt, the charity said. This was due to either their own habit or someone else’s.</Para><Para>Meanwhile, the number of problem gamblers seen by One Hope Centre fluctuates yearly, but it helps about 200 to 300 clients each year, said general manager Joanna Kong.</Para><Para>The non-profit has seen a “noticeable increase” in the number of problem gamblers aged below 30 seeking help.</Para><Para>Given the long queues reported at lottery and sports betting operator Singapore Pools’ outlets, Ms Kong said she is not surprised that a larger proportion of Singaporeans are trying their luck with 4D or Toto.</Para><Para>“It is an avenue for people to gamble easily, with the convenience of these gambling outlets in the heartlands,” she said.</Para><Para>Awareness of avenues for help could be increasing, said the NCPG.</Para><Para>Those who gambled showed lower rates of “poor self-control”, while the number of calls or webchats from those needing help last year also fell by about 18 per cent when compared to 2016.</Para></TailParas><Byline fid="by" index="field">Siau Ming En </Byline><Credit fid="cr" index="field"></Credit><Contact fid="ct" index="field"></Contact><Notes fid="rf" index="field"></Notes><Art fid="art" index="field"></Art><Copyright fid="cy" index="field">(c) 2018. MediaCorp Press Ltd. </Copyright></Article></ArchiveDoc><AdocTOC adoctype="article"><Item size="0" ref="distdoc:archive/ArchiveDoc::Article" type="arttext"></Item><Item size="0" ref="distdoc:archive/InvertText" type="invtext"></Item></AdocTOC></DistDoc>

