<DistDoc action="rep" dist="dist_id" distdocver="05.1" an="WSJO000020180322ee3m0002t" doctype="article"><SelectData><FolderName id="302210958" rl="100">WSJ</FolderName></SelectData><ReplyItem lang="en"><BaseLang value="en" fid="la"/><IPDocId fid="id">2E5BA8CA15D6757648D676F8C703695A SB12695538546930973963904584116263898650206</IPDocId><AccessionNo value="WSJO000020180322ee3m0002t" fid="an"/><Num value="746" fid="wc"/><Date value="20180322" fid="pd"/><Time value="013700" fid="et"/><SrcCode value="wsjo" fid="sc"/><SrcName fid="sn">The Wall Street Journal Online</SrcName><TruncRules><XS value="28"/><S value="60"/><M value="80"/><L value="132"/></TruncRules><Title fid="hl"><SectionName fid="se">Markets</SectionName><ColumnName fid="clm"></ColumnName><Headline fid="hd"><Para lang="en">Reformer Guo Shuqing to Oversee China's Banks and Insurers; Appointment comes amid signs of rising distrust of Western market models within the Communist Party</Para></Headline></Title><Snippet><Para>BEIJING—China's banking czar is getting a broader remit to oversee not only the nation's lenders but also the troubled insurance sector, an effort by Beijing to beat back risks from an economy and financial sector fueled by debt.</Para></Snippet><Byline fid="by">By Chao Deng </Byline><Credit fid="cr"></Credit><Copyright fid="cy">Copyright 2018 Dow Jones &amp; Company, Inc. All Rights Reserved. </Copyright><CodeSets><CSet fid="co"><Code value="cibklm"/></CSet><CSet fid="in"><Code value="i81402"/><Code value="i814"/><Code value="ibnk"/><Code value="ifinal"/></CSet><CSet fid="re"><Code value="china"/><Code value="beijin"/><Code value="asiaz"/><Code value="easiaz"/><Code value="apacz"/><Code value="bric"/><Code value="chinaz"/><Code value="devgcoz"/><Code value="dvpcoz"/></CSet><CSet fid="ns"><Code value="c13"/><Code value="gcat"/><Code value="ginda"/><Code value="gpir"/><Code value="mcat"/><Code value="ccat"/><Code value="gpol"/><Code value="ncat"/><Code value="nfact"/><Code value="nfce"/><Code value="nfcpin"/></CSet></CodeSets></ReplyItem><MetadataPT><DocData><DocType value="article" fid="fmt"/><IPDocId fid="id">2E5BA8CA15D6757648D676F8C703695A SB12695538546930973963904584116263898650206</IPDocId><AccessionNo value="WSJO000020180322ee3m0002t" fid="an"/><Num value="746" fid="wc"/><Num value="3579" fid="cc"/><Date value="20180322" fid="pd"/><Date value="20180322" fid="upd"/><Date value="20180322" fid="md"/><Time value="013700" fid="et"/><Time value="013718" fid="upt"/><Time value="145207" fid="mt"/><BaseLang value="en" fid="la"/><Editor value="" fid="rve"/><RevisionNo value="2" fid="rvn"/></DocData><PubData><Restrictor fid="rst"><Code value="FSPNORMAWS0300"/><Code value="WSJO"/><Code value="fspFileId275600643"/><Code value="FUT"/><Code value="CLNTALL"/><Code value="CTGSMFS"/><Code value="CTGWSJ"/><Code value="DEEPWSJP"/><Code value="EN"/><Code value="IBNK"/><Code value="IFINAL"/><Code value="IINV"/><Code value="NAMZ"/><Code value="SFWSJ"/><Code value="TBAC"/><Code value="TBED"/><Code value="TBIZ"/><Code value="TBRK"/><Code value="TDJP"/><Code value="TDJWMNP"/><Code value="TFCDLIC"/><Code value="TFIN"/><Code value="TIAS"/><Code value="TIBMNB"/><Code value="TIMG"/><Code value="TINT"/><Code value="TIOP"/><Code value="TMNB"/><Code value="TMNBUS"/><Code value="TNPS"/><Code value="TNWP"/><Code value="TNWPN"/><Code value="TOPUSA"/><Code value="TSCH"/><Code value="TTRD"/><Code value="TTRK"/><Code value="TUSN"/><Code value="TWMSA"/><Code value="TYAS"/><Code value="TYLA"/><Code value="USA"/><Code value="fspWebpage"/><Code value="djrcef"/><Code value="MPCV1M9M1B1"/><Code value="MPCEnvPROD"/><Code value="MPCDocHashBD58C40D2B76C932"/><Code value="FSP2YESCOOC"/><Code value="FSP2YESCOCOMOC"/><Code value="FSP2YESCOORGOC"/><Code value="FSPRBC"/><Code value="FSPRBCCO"/><Code value="FSPRBCORG"/><Code value="FSP2YESCO"/><Code value="FSP2YESCOORG"/><Code value="FSPCATEGORIZER"/><Code value="FSPCATIN"/><Code value="FSP2YESIN"/><Code value="FSPRBCIN"/><Code value="FSPRBCNS"/><Code value="FSP2YESNS"/><Code value="FSPCATRE"/><Code value="FSPRBCRE"/><Code value="FSP2YESRE"/><Code value="FSP2YESPEOC"/><Code value="FSPRBC621526"/><Code value="FSPRBC631631"/><Code value="FSPRBC680480"/><Code value="FSPRBC721164"/><Code value="FSPRBC801061"/><Code value="FSPRBC801869"/><Code value="FSPRBC818182"/><Code value="FSPRBC828384"/><Code value="FSPRBC857677"/><Code value="FSPRBC860298"/><Code value="FSPRBC860372"/><Code value="FSPRBC860380"/><Code value="FSPRBC861005"/><Code value="FSPRBC861099"/><Code value="FSPRBC861199"/><Code value="FSPRBC861788"/><Code value="FSPRBC861917"/><Code value="MPCCL"/><Code value="MPCJP"/><Code value="MPCKW"/><Code value="MPCKP"/><Code value="MPCESRE"/><Code value="MPCESIN"/><Code value="MPCESNS"/><Code value="FSP2AC"/></Restrictor><IPId value="DJENT" fid="ip"/><PublisherN fid="pub">Dow Jones &amp; Company, Inc.</PublisherN><AttribCode value="WSJO2" fid="atr"/><SrcCode value="WSJO" fid="sc"/><SrcName fid="sn">The Wall Street Journal Online</SrcName><Logo img="wsjoLogo.gif" link="" src="http://logos.factiva.com"/></PubData><CodeSets><CSet fid="co"><Code value="cibklm"><CodeD index="no" lang="en">China Banking Regulatory Commission</CodeD><CodeI org="rbc" action="add"><CodeA name="rule" value="721164"/><CodeA name="db" value="prbc---00018572-20180322-075252"/></CodeI><CodeI org="validation" action="add"><CodeA name="db" value="pedv---00000998-20180321-161406"/><CodeA name="status" value="active"/></CodeI></Code></CSet><CSet fid="in"><Code value="i81402"><CodeD index="no" lang="en">Commercial Banking</CodeD><CodeI org="categoriser" action="add"><CodeA name="db" value="es-EnglishIN_en_20180319140637"/><CodeA name="es_score" value="152"/></CodeI><CodeI org="validation" action="add"><CodeA name="db" value="pedv---00000998-20180321-161406"/><CodeA name="status" value="active"/></CodeI><CodeI org="hierarchy" action="add"><CodeA name="db" value="pedv---00000998-20180321-161406"/><CodeA name="nodelevel" value="3"/></CodeI></Code><Code value="i814"><CodeD index="no" lang="en">Banking</CodeD><CodeI org="rbc" action="add"><CodeA name="rule" value="861788"/><CodeA name="db" value="prbc---00018572-20180322-075252"/></CodeI><CodeI org="expansion" action="add"><CodeA name="db" value="pedv---00000998-20180321-161406"/><CodeA name="root" value="in:i81402"/></CodeI><CodeI org="validation" action="add"><CodeA name="db" value="pedv---00000998-20180321-161406"/><CodeA name="status" value="active"/></CodeI><CodeI org="hierarchy" action="add"><CodeA name="db" value="pedv---00000998-20180321-161406"/><CodeA name="nodelevel" value="2"/></CodeI></Code><Code value="ibnk"><CodeD index="no" lang="en">Banking/Credit</CodeD><CodeI org="rbc" action="add"><CodeA name="rule" value="631631"/><CodeA name="db" value="prbc---00018572-20180322-075252"/><CodeA name="rule" value="801869"/></CodeI><CodeI org="expansion" action="add"><CodeA name="db" value="pedv---00000998-20180321-161406"/><CodeA name="root" value="in:i81402"/><CodeA name="root" value="in:i814"/></CodeI><CodeI org="validation" action="add"><CodeA name="db" value="pedv---00000998-20180321-161406"/><CodeA name="status" value="active"/></CodeI><CodeI org="hierarchy" action="add"><CodeA name="db" value="pedv---00000998-20180321-161406"/><CodeA name="nodelevel" value="1"/></CodeI></Code><Code value="ifinal"><CodeD index="no" lang="en">Financial Services</CodeD><CodeI org="rbc" action="add"><CodeA name="rule" value="861917"/><CodeA name="db" value="prbc---00018572-20180322-075252"/></CodeI><CodeI org="expansion" action="add"><CodeA name="db" value="pedv---00000998-20180321-161406"/><CodeA name="root" value="in:i81402"/><CodeA name="root" value="in:i814"/><CodeA name="root" value="in:ibnk"/></CodeI><CodeI org="validation" action="add"><CodeA name="db" value="pedv---00000998-20180321-161406"/><CodeA name="status" value="active"/></CodeI><CodeI org="hierarchy" action="add"><CodeA name="db" value="pedv---00000998-20180321-161406"/><CodeA name="nodelevel" value="0"/></CodeI></Code></CSet><CSet fid="re"><Code value="china"><CodeD index="no" lang="en">China</CodeD><CodeI org="categoriser" action="add"><CodeA name="db" value="es-EnglishRE_en_20180319142019"/><CodeA name="es_score" value="304"/></CodeI><CodeI org="rbc" action="add"><CodeA name="rule" value="861099"/><CodeA name="db" value="prbc---00018572-20180322-075252"/><CodeA name="rule" value="621526"/></CodeI><CodeI org="expansion" action="add"><CodeA name="db" value="pedv---00000998-20180321-161406"/><CodeA name="root" value="re:beijin"/></CodeI><CodeI org="validation" action="add"><CodeA name="db" value="pedv---00000998-20180321-161406"/><CodeA name="status" value="active"/></CodeI><CodeI org="hierarchy" action="add"><CodeA name="db" value="pedv---00000998-20180321-161406"/><CodeA name="nodelevel" value="1"/><CodeA name="nodelevel" value="2"/><CodeA name="nodelevel" value="3"/></CodeI></Code><Code value="beijin"><CodeD index="no" lang="en">Beijing</CodeD><CodeI org="categoriser" action="add"><CodeA name="db" value="es-EnglishRE_en_20180319142019"/><CodeA name="es_score" value="180"/></CodeI><CodeI org="rbc" action="add"><CodeA name="rule" value="680480"/><CodeA name="db" value="prbc---00018572-20180322-075252"/></CodeI><CodeI org="validation" action="add"><CodeA name="db" value="pedv---00000998-20180321-161406"/><CodeA name="status" value="active"/></CodeI><CodeI org="hierarchy" action="add"><CodeA name="db" value="pedv---00000998-20180321-161406"/><CodeA name="nodelevel" value="2"/><CodeA name="nodelevel" value="3"/><CodeA name="nodelevel" value="4"/></CodeI></Code><Code value="asiaz"><CodeD index="no" lang="en">Asia</CodeD><CodeI org="rbc" action="add"><CodeA name="rule" value="861005"/><CodeA name="db" value="prbc---00018572-20180322-075252"/></CodeI><CodeI org="expansion" action="add"><CodeA name="db" value="pedv---00000998-20180321-161406"/><CodeA name="root" value="re:china"/><CodeA name="root" value="re:beijin"/><CodeA name="root" value="re:easiaz"/></CodeI><CodeI org="validation" action="add"><CodeA name="db" value="pedv---00000998-20180321-161406"/><CodeA name="status" value="active"/></CodeI><CodeI org="hierarchy" action="add"><CodeA name="db" value="pedv---00000998-20180321-161406"/><CodeA name="nodelevel" value="0"/></CodeI></Code><Code value="easiaz"><CodeD index="no" lang="en">Eastern Asia</CodeD><CodeI org="rbc" action="add"><CodeA name="rule" value="861199"/><CodeA name="db" value="prbc---00018572-20180322-075252"/></CodeI><CodeI org="expansion" action="add"><CodeA name="db" value="pedv---00000998-20180321-161406"/><CodeA name="root" value="re:china"/><CodeA name="root" value="re:beijin"/></CodeI><CodeI org="validation" action="add"><CodeA name="db" value="pedv---00000998-20180321-161406"/><CodeA name="status" value="active"/></CodeI><CodeI org="hierarchy" action="add"><CodeA name="db" value="pedv---00000998-20180321-161406"/><CodeA name="nodelevel" value="1"/></CodeI></Code><Code value="apacz"><CodeD index="no" lang="en">Asia Pacific</CodeD><CodeI org="expansion" action="add"><CodeA name="db" value="pedv---00000998-20180321-161406"/><CodeA name="root" value="re:china"/><CodeA name="root" value="re:beijin"/><CodeA name="root" value="re:easiaz"/></CodeI><CodeI org="validation" action="add"><CodeA name="db" value="pedv---00000998-20180321-161406"/><CodeA name="status" value="active"/></CodeI><CodeI org="hierarchy" action="add"><CodeA name="db" value="pedv---00000998-20180321-161406"/><CodeA name="nodelevel" value="0"/></CodeI></Code><Code value="bric"><CodeD index="no" lang="en">BRICS Countries</CodeD><CodeI org="expansion" action="add"><CodeA name="db" value="pedv---00000998-20180321-161406"/><CodeA name="root" value="re:china"/><CodeA name="root" value="re:beijin"/></CodeI><CodeI org="validation" action="add"><CodeA name="db" value="pedv---00000998-20180321-161406"/><CodeA name="status" value="active"/></CodeI><CodeI org="hierarchy" action="add"><CodeA name="db" value="pedv---00000998-20180321-161406"/><CodeA name="nodelevel" value="1"/></CodeI></Code><Code value="chinaz"><CodeD index="no" lang="en">Greater China</CodeD><CodeI org="expansion" action="add"><CodeA name="db" value="pedv---00000998-20180321-161406"/><CodeA name="root" value="re:china"/><CodeA name="root" value="re:beijin"/></CodeI><CodeI org="validation" action="add"><CodeA name="db" value="pedv---00000998-20180321-161406"/><CodeA name="status" value="active"/></CodeI><CodeI org="hierarchy" action="add"><CodeA name="db" value="pedv---00000998-20180321-161406"/><CodeA name="nodelevel" value="2"/></CodeI></Code><Code value="devgcoz"><CodeD index="no" lang="en">Emerging Market Countries</CodeD><CodeI org="expansion" action="add"><CodeA name="db" value="pedv---00000998-20180321-161406"/><CodeA name="root" value="re:china"/><CodeA name="root" value="re:beijin"/></CodeI><CodeI org="validation" action="add"><CodeA name="db" value="pedv---00000998-20180321-161406"/><CodeA name="status" value="active"/></CodeI><CodeI org="hierarchy" action="add"><CodeA name="db" value="pedv---00000998-20180321-161406"/><CodeA name="nodelevel" value="0"/></CodeI></Code><Code value="dvpcoz"><CodeD index="no" lang="en">Developing Economies</CodeD><CodeI org="expansion" action="add"><CodeA name="db" value="pedv---00000998-20180321-161406"/><CodeA name="root" value="re:china"/><CodeA name="root" value="re:beijin"/></CodeI><CodeI org="validation" action="add"><CodeA name="db" value="pedv---00000998-20180321-161406"/><CodeA name="status" value="active"/></CodeI><CodeI org="hierarchy" action="add"><CodeA name="db" value="pedv---00000998-20180321-161406"/><CodeA name="nodelevel" value="0"/></CodeI></Code></CSet><CSet fid="ns"><Code value="c13"><CodeD index="no" lang="en">Regulation/Government Policy</CodeD><CodeI org="rbc" action="add"><CodeA name="rule" value="828384"/><CodeA name="db" value="prbc---00018572-20180322-075252"/><CodeA name="rule" value="860372"/></CodeI><CodeI org="validation" action="add"><CodeA name="db" value="pedv---00000998-20180321-161406"/><CodeA name="status" value="active"/></CodeI><CodeI org="hierarchy" action="add"><CodeA name="db" value="pedv---00000998-20180321-161406"/><CodeA name="nodelevel" value="1"/></CodeI></Code><Code value="gcat"><CodeD index="no" lang="en">Political/General News</CodeD><CodeI org="rbc" action="add"><CodeA name="rule" value="860298"/><CodeA name="db" value="prbc---00018572-20180322-075252"/></CodeI><CodeI org="expansion" action="add"><CodeA name="db" value="pedv---00000998-20180321-161406"/><CodeA name="root" value="ns:ginda"/><CodeA name="root" value="ns:gpir"/></CodeI><CodeI org="validation" action="add"><CodeA name="db" value="pedv---00000998-20180321-161406"/><CodeA name="status" value="active"/></CodeI><CodeI org="hierarchy" action="add"><CodeA name="db" value="pedv---00000998-20180321-161406"/><CodeA name="nodelevel" value="0"/></CodeI></Code><Code value="ginda"><CodeD index="no" lang="en">Independent Advisory Bodies</CodeD><CodeI org="rbc" action="add"><CodeA name="rule" value="801061"/><CodeA name="db" value="prbc---00018572-20180322-075252"/></CodeI><CodeI org="validation" action="add"><CodeA name="db" value="pedv---00000998-20180321-161406"/><CodeA name="status" value="active"/></CodeI><CodeI org="hierarchy" action="add"><CodeA name="db" value="pedv---00000998-20180321-161406"/><CodeA name="nodelevel" value="3"/></CodeI></Code><Code value="gpir"><CodeD index="no" lang="en">Politics/International Relations</CodeD><CodeI org="rbc" action="add"><CodeA name="rule" value="860380"/><CodeA name="db" value="prbc---00018572-20180322-075252"/></CodeI><CodeI org="expansion" action="add"><CodeA name="db" value="pedv---00000998-20180321-161406"/><CodeA name="root" value="ns:ginda"/></CodeI><CodeI org="validation" action="add"><CodeA name="db" value="pedv---00000998-20180321-161406"/><CodeA name="status" value="active"/></CodeI><CodeI org="hierarchy" action="add"><CodeA name="db" value="pedv---00000998-20180321-161406"/><CodeA name="nodelevel" value="1"/></CodeI></Code><Code value="mcat"><CodeD index="no" lang="en">Commodity/Financial Market News</CodeD><CodeI org="rbc" action="add"><CodeA name="rule" value="857677"/><CodeA name="db" value="prbc---00018572-20180322-075252"/></CodeI><CodeI org="validation" action="add"><CodeA name="db" value="pedv---00000998-20180321-161406"/><CodeA name="status" value="active"/></CodeI><CodeI org="hierarchy" action="add"><CodeA name="db" value="pedv---00000998-20180321-161406"/><CodeA name="nodelevel" value="0"/></CodeI></Code><Code value="ccat"><CodeD index="no" lang="en">Corporate/Industrial News</CodeD><CodeI org="expansion" action="add"><CodeA name="db" value="pedv---00000998-20180321-161406"/><CodeA name="root" value="ns:c13"/></CodeI><CodeI org="validation" action="add"><CodeA name="db" value="pedv---00000998-20180321-161406"/><CodeA name="status" value="active"/></CodeI><CodeI org="hierarchy" action="add"><CodeA name="db" value="pedv---00000998-20180321-161406"/><CodeA name="nodelevel" value="0"/></CodeI></Code><Code value="gpol"><CodeD index="no" lang="en">Domestic Politics</CodeD><CodeI org="expansion" action="add"><CodeA name="db" value="pedv---00000998-20180321-161406"/><CodeA name="root" value="ns:ginda"/></CodeI><CodeI org="validation" action="add"><CodeA name="db" value="pedv---00000998-20180321-161406"/><CodeA name="status" value="active"/></CodeI><CodeI org="hierarchy" action="add"><CodeA name="db" value="pedv---00000998-20180321-161406"/><CodeA name="nodelevel" value="2"/></CodeI></Code><Code value="ncat"><CodeD index="no" lang="en">Content Types</CodeD><CodeI org="expansion" action="add"><CodeA name="db" value="pedv---00000998-20180321-161406"/><CodeA name="root" value="ns:c13"/><CodeA name="root" value="ns:mcat"/></CodeI><CodeI org="validation" action="add"><CodeA name="db" value="pedv---00000998-20180321-161406"/><CodeA name="status" value="active"/></CodeI></Code><Code value="nfact"><CodeD index="no" lang="en">Factiva Filters</CodeD><CodeI org="expansion" action="add"><CodeA name="db" value="pedv---00000998-20180321-161406"/><CodeA name="root" value="ns:c13"/><CodeA name="root" value="ns:mcat"/></CodeI><CodeI org="validation" action="add"><CodeA name="db" value="pedv---00000998-20180321-161406"/><CodeA name="status" value="active"/></CodeI></Code><Code value="nfce"><CodeD index="no" lang="en">C&amp;E Exclusion Filter</CodeD><CodeI org="expansion" action="add"><CodeA name="db" value="pedv---00000998-20180321-161406"/><CodeA name="root" value="ns:mcat"/></CodeI><CodeI org="validation" action="add"><CodeA name="db" value="pedv---00000998-20180321-161406"/><CodeA name="status" value="active"/></CodeI></Code><Code value="nfcpin"><CodeD index="no" lang="en">C&amp;E Industry News Filter</CodeD><CodeI org="expansion" action="add"><CodeA name="db" value="pedv---00000998-20180321-161406"/><CodeA name="root" value="ns:c13"/></CodeI><CodeI org="validation" action="add"><CodeA name="db" value="pedv---00000998-20180321-161406"/><CodeA name="status" value="active"/></CodeI></Code></CSet></CodeSets><DescTPC fid="de"><DescField fid="ipc">I/BNK M/FCL N/GEN N/PBOC N/PBP N/PLT R/ASI R/CH R/FEO </DescField><DescField fid="ipd">WSJ WSJ.com WSJ.com Site Search WSJAsia WSJEurope WSJ Japanese Online WSJ-PRO-WSJ.com WSJSunday CHINA BANKING CHINA BANKING REGULATOR CHINA BANKING REGULATORY COMMISSION CHINA CREDIT GUO SHUQING LIU HE XI JINPING SB126955385469309739639045841162638986502061 Yi Gang Zhou Xiaochuan PRO SYND Financial Regulation WSJ-PRO-FR WSJ-PRO-NP CODES_REVIEWED Top News FINREGTOPNEWS Banking FRBANKING Chinese Regulators FRCHINESEREGULATORS Markets FRMARKETS Markets Main </DescField><DescField fid="ipcns">OMKM </DescField></DescTPC></MetadataPT><ArchiveDoc xml:space="preserve"><Article markup="pp0" lang="en" index="field"><HandL fid="hlp"><Title fid="hl"><SectionName fid="se" index="field">Markets</SectionName><ColumnName fid="clm" index="field"></ColumnName><Headline fid="hd"><Para lang="en">Reformer Guo Shuqing to Oversee China's Banks and Insurers; Appointment comes amid signs of rising distrust of Western market models within the Communist Party</Para></Headline></Title><LeadPara fid="lp"><Para>BEIJING—China's banking czar is getting a broader remit to <ELink type="webpage" ref="https://www.wsj.com/articles/china-unveils-overhaul-of-government-bureaucracy-1520905490">oversee not only the nation's lenders but also the troubled insurance sector</ELink>, an effort by Beijing to beat back risks from an economy and financial sector fueled by debt.</Para><Para>Guo Shuqing, a known pro-market reformer and current chairman of the China Banking Regulatory Commission, will lead a newly-combined banking and insurance regulatory commission, according to people familiar with the matter.</Para></LeadPara></HandL><TailParas fid="td"><Para>Mr. Guo was among officials shortlisted last year to succeed Zhou Xiaochuan, who has served as governor of the People's Bank of China for the last 15 years. <ELink type="webpage" ref="https://www.wsj.com/articles/yi-gang-picked-to-take-helm-of-peoples-bank-of-china-1521375330">But that spot this week went to Mr. Zhou's protégé</ELink>, longtime central-bank official Yi Gang. One theory among analysts is that top leaders saw Mr. Guo as too aggressive in pushing for change at a time when financial stability has been the most pressing issue.</Para><Para>"He's a person who wants to do things, and dares to do things," says Liu Shengjun, head of China Financial Reform Institute, a think tank in Shanghai.</Para><Para>China's legislature approved a plan to combine the agencies last week and with Mr. Guo being passed over for the top job at the PBOC, his promotion to head the combined regulator was expected. Top officials from both commissions held a meeting Wednesday, where Mr. Guo's appointment was announced, according to people who attended.</Para><Para>Mr. Guo called for stabilizing the regulatory teams and for work to continue without disruption, according to an official who was there.</Para><Para>It wasn't clear when the appointment would be made public. A spokesman at the China Banking Regulatory Commission declined to comment.</Para><Para>Mr. Guo has deep experience in the financial sector and has been a warrior in Beijing's fight against rising debt. He surprised markets last year by initiating a thorough investigation of the industry's practices, in tandem with a blizzard of new rules and fines to curb risky behavior by banks.</Para><Para>"At the high level, there's a confidence in him," says Zhu Ning, a finance professor at Tsinghua University. Mr. Guo, he said, has proven himself to Beijing both at the local level, as a former governor of eastern Shandong province, and at the center, having led the securities watchdog and the banking regulator.</Para><Para>As head of a super regulator, Mr. Guo will take on an even bigger role in Beijing's financial-risk crackdown. He will be responsible for reining in risky investments and lending practices by both banks and insurers.</Para><Para>At the core of Beijing's efforts to slow the growth of debt in the overall economy is repairing the banking system, which has long been lending to bloated state-owned enterprises. Banks have collaborated with nonbanks to form a shadow-lending network in recent years that Beijing is trying to control.</Para><Para>Mr. Guo will be also be tasked with warding off emerging systemic threats, or problems with any one financial institution from spreading and potentially causing a panic in the broader economy and society.</Para><Para>The domestic insurance industry has boomed in recent years by selling high-yielding investment products, much like the wealth-management products that smaller banks in particular have depended on for growth. Mr. Guo's remit now includes Anbang Insurance Group Co., a high-profile offender that the government seized last month.</Para><Para>At the same time, regulators and people in the industry are cautious about their expectations of Mr. Guo, given signs of rising distrust of Western market models within the Communist Party and a power grab by President Xi Jinping, which they say is squeezing reform efforts.</Para><Para>Among potential flashpoints will be how to encourage the unwinding of banking and insurance products heavily invested in domestic stocks and bonds, and keeping a check on bank loans that end up in real estate, a key pillar of Chinese economic growth.</Para><Para>"No one can implement reform when there are financial risks," says China Financial Reform Institute's Mr. Liu. That includes Mr. Guo and even his boss, he says.</Para><Para>The banking-insurance regulator is ultimately under the purview of Liu He, a confidant of Mr. Xi who <ELink type="webpage" ref="https://www.wsj.com/articles/blessed-by-xi-jinping-the-new-captain-of-chinas-economy-1519688592">heads a top-level committee</ELink> launched last year to streamline financial regulation and implement overarching financial policy.</Para><Para>Write to Chao Deng at <ELink type="webpage" ref="mailto:Chao.Deng@wsj.com">Chao.Deng@wsj.com</ELink></Para></TailParas><Byline fid="by" index="field">By Chao Deng </Byline><Credit fid="cr" index="field"></Credit><Contact fid="ct" index="field"></Contact><Notes fid="rf" index="field"></Notes><Art fid="art" index="field"></Art><Copyright fid="cy" index="field">Copyright 2018 Dow Jones &amp; Company, Inc. All Rights Reserved. </Copyright></Article></ArchiveDoc><AdocTOC adoctype="article"><Item size="0" ref="distdoc:archive/ArchiveDoc::Article" type="arttext"></Item><Item size="0" ref="distdoc:archive/InvertText" type="invtext"></Item><Item subtype="primary" size="0" ref="https://www.wsj.com/articles/reformer-guo-shuqing-to-oversee-chinas-banks-and-insurers-1521682625" type="webpage"></Item></AdocTOC></DistDoc>

